MANIFEST.in
README.rst
bootstrap-buildout.py
buildout.cfg
setup.py
version.txt
antispoofing/__init__.py
antispoofing.lbp.egg-info/PKG-INFO
antispoofing.lbp.egg-info/SOURCES.txt
antispoofing.lbp.egg-info/dependency_links.txt
antispoofing.lbp.egg-info/entry_points.txt
antispoofing.lbp.egg-info/requires.txt
antispoofing.lbp.egg-info/top_level.txt
antispoofing.lbp.egg-info/zip-safe
antispoofing/lbp/__init__.py
antispoofing/lbp/helpers/__init__.py
antispoofing/lbp/helpers/database.py
antispoofing/lbp/helpers/score_manipulate.py
antispoofing/lbp/script/__init__.py
antispoofing/lbp/script/calcframelbp.py
antispoofing/lbp/script/calcframelbp_multiscale.py
antispoofing/lbp/script/calchog.py
antispoofing/lbp/script/calclbp.py
antispoofing/lbp/script/check_rotated_videos.py
antispoofing/lbp/script/cmphistmodels.py
antispoofing/lbp/script/ldatrain_lbp.py
antispoofing/lbp/script/mkhistmodel.py
antispoofing/lbp/script/svmeval_lbp.py
antispoofing/lbp/script/svmtrain_lbp.py
antispoofing/lbp/spoof/__init__.py
antispoofing/lbp/spoof/calclbp.py
antispoofing/lbp/spoof/chi2.py