Metadata-Version: 1.0
Name: antispoofing.lbp
Version: 2.0.4
Summary: Texture (LBP) based counter-measures for the REPLAY-ATTACK database
Home-page: http://pypi.python.org/pypi/antispoofing.lbp
Author: Ivana Chingovska
Author-email: ivana.chingovska@idiap.ch
License: GPLv3
Keywords: antispoofing texture,LBP,face spoofing attacks,face spoofing database,bob,xbob
Platform: UNKNOWN
